{
  "currentState": "role_activated_with_memory",
  "stateHistory": [
    {
      "from": "initial",
      "command": "welcome",
      "timestamp": "2025-06-26T13:31:33.563Z",
      "args": []
    },
    {
      "from": "role_discovery",
      "command": "init",
      "timestamp": "2025-06-26T13:31:44.495Z",
      "args": [
        {
          "workingDirectory": "/Users/carson/Desktop/TraeCN"
        }
      ]
    },
    {
      "from": "initialized",
      "command": "welcome",
      "timestamp": "2025-06-26T13:31:55.008Z",
      "args": []
    },
    {
      "from": "role_discovery",
      "command": "action",
      "timestamp": "2025-06-26T13:32:05.666Z",
      "args": [
        "nuwa"
      ]
    },
    {
      "from": "role_activated_with_memory",
      "command": "action",
      "timestamp": "2025-06-26T13:32:39.735Z",
      "args": [
        "nuwa"
      ]
    },
    {
      "from": "role_activated_with_memory",
      "command": "action",
      "timestamp": "2025-06-26T13:33:19.319Z",
      "args": [
        "nuwa"
      ]
    },
    {
      "from": "role_activated_with_memory",
      "command": "action",
      "timestamp": "2025-06-26T13:34:11.083Z",
      "args": [
        "event-planning-expert"
      ]
    },
    {
      "from": "role_activated_with_memory",
      "command": "init",
      "timestamp": "2025-06-26T13:34:21.862Z",
      "args": [
        {
          "workingDirectory": "/Users/carson/Desktop/TraeCN"
        }
      ]
    },
    {
      "from": "initialized",
      "command": "welcome",
      "timestamp": "2025-06-26T13:34:29.125Z",
      "args": []
    },
    {
      "from": "role_discovery",
      "command": "action",
      "timestamp": "2025-06-26T13:35:02.739Z",
      "args": [
        "event-planning-expert"
      ]
    },
    {
      "from": "role_activated_with_memory",
      "command": "init",
      "timestamp": "2025-06-26T13:35:46.161Z",
      "args": [
        {
          "workingDirectory": "/Users/carson/Desktop/TraeCN"
        }
      ]
    },
    {
      "from": "initialized",
      "command": "init",
      "timestamp": "2025-06-26T13:44:35.319Z",
      "args": [
        {
          "workingDirectory": "/Users/carson/Desktop/TraeCN"
        }
      ]
    },
    {
      "from": "initialized",
      "command": "init",
      "timestamp": "2025-06-27T15:16:02.603Z",
      "args": [
        {
          "workingDirectory": "/Users/carson/Desktop/deepracticexc"
        }
      ]
    },
    {
      "from": "initialized",
      "command": "welcome",
      "timestamp": "2025-06-27T15:16:06.242Z",
      "args": []
    },
    {
      "from": "role_discovery",
      "command": "init",
      "timestamp": "2025-06-27T15:17:17.637Z",
      "args": [
        {
          "workingDirectory": "/Users/carson/Desktop/deepracticexc"
        }
      ]
    },
    {
      "from": "initialized",
      "command": "welcome",
      "timestamp": "2025-06-27T15:17:18.064Z",
      "args": []
    },
    {
      "from": "role_discovery",
      "command": "action",
      "timestamp": "2025-06-27T15:17:23.580Z",
      "args": [
        "nuwa"
      ]
    },
    {
      "from": "role_activated_with_memory",
      "command": "init",
      "timestamp": "2025-06-27T15:18:21.781Z",
      "args": [
        {
          "workingDirectory": "/Users/carson/Desktop/deepracticexc"
        }
      ]
    },
    {
      "from": "initialized",
      "command": "welcome",
      "timestamp": "2025-06-27T15:18:26.781Z",
      "args": []
    },
    {
      "from": "role_discovery",
      "command": "action",
      "timestamp": "2025-06-27T15:18:31.695Z",
      "args": [
        "nuwa"
      ]
    },
    {
      "from": "role_activated_with_memory",
      "command": "action",
      "timestamp": "2025-06-27T15:23:40.621Z",
      "args": [
        "github-oss-expert"
      ]
    },
    {
      "from": "role_activated_with_memory",
      "command": "init",
      "timestamp": "2025-06-27T15:23:44.442Z",
      "args": [
        {
          "workingDirectory": "/Users/carson/Desktop/deepracticexc"
        }
      ]
    },
    {
      "from": "initialized",
      "command": "action",
      "timestamp": "2025-06-27T15:23:49.330Z",
      "args": [
        "github-oss-expert"
      ]
    },
    {
      "from": "role_activated_with_memory",
      "command": "action",
      "timestamp": "2025-06-27T15:27:49.463Z",
      "args": [
        "github-oss-expert"
      ]
    },
    {
      "from": "role_activated_with_memory",
      "command": "remember",
      "timestamp": "2025-06-27T15:28:09.370Z",
      "args": [
        "寶哥的每日工作重點包括：1. 準備HWDC投稿，PPT將參考deepractice.ai/presentation/heywhale-story-presentation的呈現形式；2. 深入理解PromptX後撰寫繁體中文文档並貢獻到github.com/deepractice/promptx；3. COSE開源商業計劃書項目 - 這是一個獨立的開源項目，定位為\"Commercial Open Source Engineering\"概念的商業計劃書，與HWDC演講沒有直接關聯。COSE是團隊原創概念，相比傳統COSS更強調AI時代的工程化特徵和標準制定能力，目標是建立GitHub倉庫展示深度實踐作為AI行業標準制定者的商業邏輯。這三項任務都是為了建立全球技術影響力和個人專家品牌。",
        "--tags",
        "寶哥工作重點 HWDC投稿 PromptX繁體中文 COSE商業計劃書 技術影響力 專家品牌"
      ]
    },
    {
      "from": "memory_saved",
      "command": "action",
      "timestamp": "2025-06-27T15:38:25.402Z",
      "args": [
        "github-oss-expert"
      ]
    }
  ],
  "lastUpdated": "2025-06-27T15:38:25.404Z"
}
